easydrive/__init__.py
easydrive/_worker.py
easydrive/control/controller.py
easydrive/control/vehicle.py
py_easydrive-1.0.0.dist-info/LICENSE
py_easydrive-1.0.0.dist-info/METADATA
py_easydrive-1.0.0.dist-info/WHEEL
py_easydrive-1.0.0.dist-info/top_level.txt
py_easydrive-1.0.0.dist-info/RECORD
