Metadata-Version: 2.1
Name: py-easydrive
Version: 1.0.0
Summary: Synchronous wrapper for py-drivesdk
Author: Pascal Rombach
Project-URL: Homepage, https://github.com/PascalRombach/py-easydrive
Project-URL: Bug Tracker, https://github.com/PascalRombach/py-easydrive/issues
Keywords: Anki Overdrive,Anki
Classifier: Programming Language :: Python :: 3
Classifier: Programming Language :: Python :: Implementation :: CPython
Classifier: License :: OSI Approved :: MIT License
Classifier: Operating System :: OS Independent
Classifier: Topic :: Education
Classifier: Topic :: Software Development :: Libraries :: Python Modules
Requires-Python: >=3.10
License-File: LICENSE
Requires-Dist: bleak
Requires-Dist: py-drivesdk
